fec_consumedlimit_soap/__init__.py
fec_consumedlimit_soap/admin.py
fec_consumedlimit_soap/apps.py
fec_consumedlimit_soap/conf.py
fec_consumedlimit_soap/config.py
fec_consumedlimit_soap/constants.py
fec_consumedlimit_soap/models.py
fec_consumedlimit_soap/service.py
fec_consumedlimit_soap/tests.py
fec_consumedlimit_soap/urls.py
fec_consumedlimit_soap/utils.py
fec_consumedlimit_soap/views.py
fec_consumedlimit_soap/migrations/0001_initial.py
fec_consumedlimit_soap/migrations/0002_auto_20180404_1313.py
fec_consumedlimit_soap/migrations/0003_auto_20180404_1408.py
fec_consumedlimit_soap/migrations/0004_auto_20180405_1158.py
fec_consumedlimit_soap/migrations/0005_fecconsumedlimit_status.py
fec_consumedlimit_soap/migrations/0006_auto_20180405_1207.py
fec_consumedlimit_soap/migrations/0007_auto_20180405_1240.py
fec_consumedlimit_soap/migrations/0008_auto_20180522_1945.py
fec_consumedlimit_soap/migrations/__init__.py
labs_integration_fec_consumedlimit_soap-0.0.29.dist-info/METADATA
labs_integration_fec_consumedlimit_soap-0.0.29.dist-info/WHEEL
labs_integration_fec_consumedlimit_soap-0.0.29.dist-info/top_level.txt
labs_integration_fec_consumedlimit_soap-0.0.29.dist-info/RECORD
